frozen_odict.py
frozen_odict-0.1.0a0.dist-info/licenses/LICENSE
frozen_odict-0.1.0a0.dist-info/METADATA
frozen_odict-0.1.0a0.dist-info/WHEEL
frozen_odict-0.1.0a0.dist-info/top_level.txt
frozen_odict-0.1.0a0.dist-info/RECORD
